composabl_grpc/main.cpython-38-x86_64-linux-gnu.so
composabl_grpc/__init__.cpython-38-x86_64-linux-gnu.so
composabl_grpc/utils/json_encoder.cpython-38-x86_64-linux-gnu.so
composabl_grpc/utils/deserializer.cpython-38-x86_64-linux-gnu.so
composabl_grpc/utils/exception_handler_grpc_server.cpython-38-x86_64-linux-gnu.so
composabl_grpc/utils/serializer_gym_env.cpython-38-x86_64-linux-gnu.so
composabl_grpc/utils/deserializer_gym_env.cpython-38-x86_64-linux-gnu.so
composabl_grpc/utils/deserializer_gym_space.cpython-38-x86_64-linux-gnu.so
composabl_grpc/utils/logger.cpython-38-x86_64-linux-gnu.so
composabl_grpc/utils/exception_handler_grpc_client.cpython-38-x86_64-linux-gnu.so
composabl_grpc/utils/deserializer_datatype.cpython-38-x86_64-linux-gnu.so
composabl_grpc/utils/__init__.cpython-38-x86_64-linux-gnu.so
composabl_grpc/utils/attr_dict.cpython-38-x86_64-linux-gnu.so
composabl_grpc/utils/serializer_gym_space.cpython-38-x86_64-linux-gnu.so
composabl_grpc/utils/serializer.cpython-38-x86_64-linux-gnu.so
composabl_grpc/utils/serializer_datatype.cpython-38-x86_64-linux-gnu.so
composabl_grpc/grpc/server/server.cpython-38-x86_64-linux-gnu.so
composabl_grpc/grpc/server/server_state.cpython-38-x86_64-linux-gnu.so
composabl_grpc/grpc/server/server_composabl.cpython-38-x86_64-linux-gnu.so
composabl_grpc/grpc/server/historian_sink.cpython-38-x86_64-linux-gnu.so
composabl_grpc/grpc/server/server_proxy.cpython-38-x86_64-linux-gnu.so
composabl_grpc/grpc/server/__init__.cpython-38-x86_64-linux-gnu.so
composabl_grpc/grpc/server/interceptors/timeout_interceptor.cpython-38-x86_64-linux-gnu.so
composabl_grpc/grpc/interceptors/timeout_interceptor.cpython-38-x86_64-linux-gnu.so
composabl_grpc/grpc/client/client_impl.cpython-38-x86_64-linux-gnu.so
composabl_grpc/grpc/client/client.cpython-38-x86_64-linux-gnu.so
composabl_grpc/proto/composabl/v1/main_pb2_grpc.py
composabl_grpc/proto/composabl/v1/main_pb2.py
composabl_grpc_dev-0.2.1.dev74.dist-info/METADATA
composabl_grpc_dev-0.2.1.dev74.dist-info/RECORD
composabl_grpc_dev-0.2.1.dev74.dist-info/entry_points.txt
composabl_grpc_dev-0.2.1.dev74.dist-info/top_level.txt
composabl_grpc_dev-0.2.1.dev74.dist-info/WHEEL
